merlin/__init__.py
merlin/data/__init__.py
merlin/data/dataloaders.py
merlin/data/download_data.py
merlin/data/monai_transforms.py
merlin/models/__init__.py
merlin/models/build.py
merlin/models/i3res.py
merlin/models/inflate.py
merlin/models/load.py
merlin/models/radiology_report_generation.py
merlin/utils/__init__.py
merlin/utils/huggingface_download.py
merlin_vlm-0.0.6.dist-info/licenses/LICENSE
merlin_vlm-0.0.6.dist-info/METADATA
merlin_vlm-0.0.6.dist-info/WHEEL
merlin_vlm-0.0.6.dist-info/top_level.txt
merlin_vlm-0.0.6.dist-info/RECORD
