Metadata-Version: 2.4
Name: merlin-vlm
Version: 0.0.6
Summary: Merlin: A Vision Language Foundation Model for 3D Computed Tomography
Author: Stanford Machine Intelligence for Medical Imaging (MIMI)
Author-email: Louis Blankemeier <louis.blankemeier@stanford.edu>, Ashwin Kumar <akkumar@stanford.edu>
License: MIT License
Project-URL: homepage, https://github.com/StanfordMIMI/Merlin
Project-URL: repository, https://github.com/StanfordMIMI/Merlin
Classifier: Development Status :: 5 - Production/Stable
Classifier: Intended Audience :: Developers
Classifier: Intended Audience :: Science/Research
Classifier: Intended Audience :: Healthcare Industry
Classifier: Programming Language :: Python :: 3
Classifier: License :: OSI Approved :: MIT License
Classifier: Topic :: Scientific/Engineering :: Artificial Intelligence
Classifier: Topic :: Scientific/Engineering :: Medical Science Apps.
Requires-Python: >=3.9
License-File: LICENSE
Requires-Dist: numpy>=1.26.4
Requires-Dist: torch>=2.1.2
Requires-Dist: monai>=1.3.0
Requires-Dist: huggingface_hub
Requires-Dist: transformers>=4.38.2
Requires-Dist: torchvision>=0.16.2
Requires-Dist: nibabel
Requires-Dist: nltk
Requires-Dist: pandas
Requires-Dist: rich
Requires-Dist: einops
Requires-Dist: peft
Requires-Dist: matplotlib
Requires-Dist: sentencepiece
Requires-Dist: protobuf
Requires-Dist: accelerate
Provides-Extra: dev
Requires-Dist: ruff; extra == "dev"
Requires-Dist: pre-commit; extra == "dev"
Requires-Dist: mdformat; extra == "dev"
Dynamic: license-file
